neobridge-0.2.1.dist-info/METADATA
neobridge-0.2.1.dist-info/WHEEL
neobridge-0.2.1.dist-info/licenses/LICENSE
neobridge/__init__.py
neobridge/code.py
neobridge/command.py
neobridge/neobridge.py
neobridge-0.2.1.dist-info/RECORD
