Metadata-Version: 2.1
Name: neobridge
Version: 0.2.1
Summary: Lets you control neopixels from your PC using a board.
Author-Email: Zayne Marsh <saynemarsh9@gmail.com>
License: MIT
Requires-Python: >=3.12
Requires-Dist: pyserial>=3.5
Requires-Dist: supervisor>=4.2.5
Requires-Dist: pyautogui>=0.9.54
Requires-Dist: typer>=0.12.1
